clerk_auth/__init__.py
clerk_auth/api_client.py
clerk_auth/apps.py
clerk_auth/authentication.py
clerk_auth/decorators.py
clerk_auth/management/__init__.py
clerk_auth/management/commands/__init__.py
clerk_auth/management/commands/sync_clerk_users.py
clerk_auth/management/commands/verify_clerk_setup.py
clerk_auth/middleware.py
clerk_auth/models.py
clerk_auth/permissions.py
clerk_auth/utils.py
clerk_auth/webhooks.py
clerk_auth_django-0.1.1.dist-info/METADATA
clerk_auth_django-0.1.1.dist-info/WHEEL
clerk_auth_django-0.1.1.dist-info/RECORD
