Metadata-Version: 2.4
Name: clerk-auth-django
Version: 0.1.1
Summary: Django REST Framework authentication library with Clerk integration
License: MIT
Keywords: django,clerk,authentication,jwt,drf,rest-framework
Author: Ernesto Martinez
Author-email: ernesto@example.com
Requires-Python: >=3.11,<4.0
Classifier: Development Status :: 4 - Beta
Classifier: Framework :: Django
Classifier: Framework :: Django :: 4.2
Classifier: Framework :: Django :: 5.0
Classifier: Intended Audience :: Developers
Classifier: License :: OSI Approved :: MIT License
Classifier: Programming Language :: Python :: 3
Classifier: Programming Language :: Python :: 3.11
Classifier: Programming Language :: Python :: 3.12
Classifier: Programming Language :: Python :: 3.13
Classifier: Programming Language :: Python :: 3.14
Requires-Dist: Django (>=4.2)
Requires-Dist: PyJWT[crypto] (>=2.8)
Requires-Dist: cryptography (>=41.0)
Requires-Dist: djangorestframework (>=3.14)
Requires-Dist: requests (>=2.31)
Project-URL: Documentation, https://github.com/ernes7/clerk-auth/tree/main/docs
Project-URL: Homepage, https://github.com/ernes7/clerk-auth
Project-URL: Repository, https://github.com/ernes7/clerk-auth
